manage_xlsx-0.1.1.dist-info/METADATA
manage_xlsx-0.1.1.dist-info/WHEEL
manage_xlsx-0.1.1.dist-info/licenses/LICENSE
xlsx/__init__.py
xlsx/xlsx.abi3.so
manage_xlsx-0.1.1.dist-info/RECORD
